{"_type":"export","__export_format":4,"__export_date":"2020-07-17T10:05:56.065Z","__export_source":"insomnia.desktop.app:v2020.3.3","resources":[{"_id":"req_ea13c29fd54c4cb39dd2e3765f6ef873","authentication":{},"body":{"mimeType":"application/json","text":"{\n\t\"macaddress\": \"11:11:11:11:11:11\", \n\t\"type\": 5,\n\t\"title\": \"Entregar material\",\n\t\"description\": \"Fazer revisão\",\n\t\"when\": \"2020-07-18T06:50:00.000\"\t\n}"},"created":1594805909987,"description":"","headers":[{"id":"pair_199edaecb954472689266051d941e611","name":"Content-Type","value":"application/json"}],"isPrivate":false,"metaSortKey":-1594955152057,"method":"POST","modified":1594978029591,"name":"create","parameters":[],"parentId":"fld_a355419b85f4449a817bb40599b7f600","settingDisableRenderRequestBody":true,"settingEncodeUrl":true,"settingFollowRedirects":"global","settingRebuildPath":true,"settingSendCookies":true,"settingStoreCookies":true,"url":"{{ URL }}/task","_type":"request"},{"_id":"fld_a355419b85f4449a817bb40599b7f600","created":1594805887168,"description":"","environment":{},"environmentPropertyOrder":null,"metaSortKey":-1594805887169,"modified":1594805887168,"name":"task","parentId":"wrk_8cebc43f2647464a91ccc2aaba04e555","_type":"request_group"},{"_id":"wrk_8cebc43f2647464a91ccc2aaba04e555","created":1588851744833,"description":"","modified":1594805868010,"name":"todo_schedule","parentId":null,"scope":null,"_type":"workspace"},{"_id":"req_11967796139d47e28b2424f0e16b40e0","authentication":{},"body":{},"created":1594955152007,"description":"","headers":[],"isPrivate":false,"metaSortKey":-1594955152007,"method":"DELETE","modified":1594955201170,"name":"delete","parameters":[],"parentId":"fld_a355419b85f4449a817bb40599b7f600","settingDisableRenderRequestBody":false,"settingEncodeUrl":true,"settingFollowRedirects":"global","settingRebuildPath":true,"settingSendCookies":true,"settingStoreCookies":true,"url":"{{ URL }}/task/5f110131a00dc61c4087d286","_type":"request"},{"_id":"req_aa3386c76ed748948df69e8c48ddca64","authentication":{},"body":{"mimeType":"application/json","text":"{\n\t\"macaddress\": \"11:11:11:11:11:11\", \n\t\"type\": 3,\n\t\"title\": \"Comprar rango\",\n\t\"description\": \"refri e pizza\",\n\t\"when\": \"2020-07-17T06:50:00.000\"\n}"},"created":1594903703488,"description":"","headers":[{"id":"pair_2ca94fb428da4f9eb1a7d91d300c2aed","name":"Content-Type","value":"application/json"}],"isPrivate":false,"metaSortKey":-1594903703488,"method":"PUT","modified":1594955902440,"name":"update","parameters":[],"parentId":"fld_a355419b85f4449a817bb40599b7f600","settingDisableRenderRequestBody":false,"settingEncodeUrl":true,"settingFollowRedirects":"global","settingRebuildPath":true,"settingSendCookies":true,"settingStoreCookies":true,"url":"{{ URL }}/task/5f0ed58f5bce423658812243","_type":"request"},{"_id":"req_3a500f8a74094065a0b794a86b1715df","authentication":{},"body":{},"created":1594956288468,"description":"","headers":[],"isPrivate":false,"metaSortKey":-1594854806737.5,"method":"PUT","modified":1594978026778,"name":"done","parameters":[],"parentId":"fld_a355419b85f4449a817bb40599b7f600","settingDisableRenderRequestBody":false,"settingEncodeUrl":true,"settingFollowRedirects":"global","settingRebuildPath":true,"settingSendCookies":true,"settingStoreCookies":true,"url":"{{ URL }}/task/5f0ed58f5bce423658812243/true","_type":"request"},{"_id":"req_8536163ac3fd4c209afe37b06e722fd8","authentication":{},"body":{},"created":1594978674425,"description":"","headers":[],"isPrivate":false,"metaSortKey":-1594848694642.9062,"method":"GET","modified":1594980198323,"name":"year","parameters":[],"parentId":"fld_a355419b85f4449a817bb40599b7f600","settingDisableRenderRequestBody":false,"settingEncodeUrl":true,"settingFollowRedirects":"global","settingRebuildPath":true,"settingSendCookies":true,"settingStoreCookies":true,"url":"{{ URL }}/task/filter/year/11:11:11:11:11:11","_type":"request"},{"_id":"req_a4f4a1065e9f4904b955212e7e9ab889","authentication":{},"body":{},"created":1594978606649,"description":"","headers":[],"isPrivate":false,"metaSortKey":-1594842582548.3125,"method":"GET","modified":1594980187511,"name":"month","parameters":[],"parentId":"fld_a355419b85f4449a817bb40599b7f600","settingDisableRenderRequestBody":false,"settingEncodeUrl":true,"settingFollowRedirects":"global","settingRebuildPath":true,"settingSendCookies":true,"settingStoreCookies":true,"url":"{{ URL }}/task/filter/month/11:11:11:11:11:11","_type":"request"},{"_id":"req_088dbd0a4ba24036841c8f614fbc08db","authentication":{},"body":{},"created":1594978553561,"description":"","headers":[],"isPrivate":false,"metaSortKey":-1594830358359.125,"method":"GET","modified":1594980177443,"name":"week","parameters":[],"parentId":"fld_a355419b85f4449a817bb40599b7f600","settingDisableRenderRequestBody":false,"settingEncodeUrl":true,"settingFollowRedirects":"global","settingRebuildPath":true,"settingSendCookies":true,"settingStoreCookies":true,"url":"{{ URL }}/task/filter/week/11:11:11:11:11:11","_type":"request"},{"_id":"req_302f57c643fe429c8c732e2406cfef1a","authentication":{},"body":{},"created":1594977955346,"description":"","headers":[],"isPrivate":false,"metaSortKey":-1594805909980.75,"method":"GET","modified":1594980163553,"name":"today","parameters":[],"parentId":"fld_a355419b85f4449a817bb40599b7f600","settingDisableRenderRequestBody":false,"settingEncodeUrl":true,"settingFollowRedirects":"global","settingRebuildPath":true,"settingSendCookies":true,"settingStoreCookies":true,"url":"{{ URL }}/task/filter/today/11:11:11:11:11:11","_type":"request"},{"_id":"req_3a7baf9b009444c09679da439bc75f07","authentication":{},"body":{},"created":1594950270350,"description":"","headers":[],"isPrivate":false,"metaSortKey":-1594805909974.5,"method":"GET","modified":1594979732159,"name":"all","parameters":[],"parentId":"fld_a355419b85f4449a817bb40599b7f600","settingDisableRenderRequestBody":false,"settingEncodeUrl":true,"settingFollowRedirects":"global","settingRebuildPath":true,"settingSendCookies":true,"settingStoreCookies":true,"url":"{{ URL }}/task/filter/all/11:11:11:11:11:11","_type":"request"},{"_id":"req_9e329c61139f4fea91cc005de14c32d8","authentication":{},"body":{},"created":1594953738733,"description":"","headers":[],"isPrivate":false,"metaSortKey":-1594805909962,"method":"GET","modified":1594978015389,"name":"show","parameters":[],"parentId":"fld_a355419b85f4449a817bb40599b7f600","settingDisableRenderRequestBody":false,"settingEncodeUrl":true,"settingFollowRedirects":"global","settingRebuildPath":true,"settingSendCookies":true,"settingStoreCookies":true,"url":"{{ URL }}/task/5f0ed58f5bce423658812243","_type":"request"},{"_id":"req_89023980d042426f9b204e17518a080a","authentication":{},"body":{},"created":1594977010124,"description":"","headers":[],"isPrivate":false,"metaSortKey":-1594805909937,"method":"GET","modified":1594980000501,"name":"late","parameters":[],"parentId":"fld_a355419b85f4449a817bb40599b7f600","settingDisableRenderRequestBody":false,"settingEncodeUrl":true,"settingFollowRedirects":"global","settingRebuildPath":true,"settingSendCookies":true,"settingStoreCookies":true,"url":"{{ URL }}/task/filter/late/11:11:11:11:11:11","_type":"request"},{"_id":"env_17259748439931175a93edd13cb42c305ab63a60","color":null,"created":1588851744891,"data":{},"dataPropertyOrder":null,"isPrivate":false,"metaSortKey":1588851744891,"modified":1588851744891,"name":"Base Environment","parentId":"wrk_8cebc43f2647464a91ccc2aaba04e555","_type":"environment"},{"_id":"jar_17259748439931175a93edd13cb42c305ab63a60","cookies":[{"creation":"2020-06-16T08:31:04.040Z","domain":"xtravagantcalcados.com.br","expires":"2020-07-16T08:31:02.000Z","extensions":["SameSite=Lax"],"hostOnly":false,"httpOnly":true,"id":"1880268756258352","key":"__cfduid","lastAccessed":"2020-06-16T08:31:04.040Z","path":"/","secure":true,"value":"dc1957d300a7c3d1b9c69641cd60e60201592296262"}],"created":1588851744897,"modified":1592296264043,"name":"Default Jar","parentId":"wrk_8cebc43f2647464a91ccc2aaba04e555","_type":"cookie_jar"},{"_id":"spc_964611216ae94aff9a20712e767efc50","contentType":"yaml","contents":"","created":1592296185542,"fileName":"Insomnia","modified":1592296185542,"parentId":"wrk_8cebc43f2647464a91ccc2aaba04e555","_type":"api_spec"},{"_id":"env_a9ade6bb0d62497588aa433b3b1d08e0","color":"#396ffb","created":1594951320651,"data":{"URL":"http://localhost:3000"},"dataPropertyOrder":{"&":["URL"]},"isPrivate":false,"metaSortKey":1594951320651,"modified":1594951407534,"name":"Desenvolvimento","parentId":"env_17259748439931175a93edd13cb42c305ab63a60","_type":"environment"}]}